jpholiday/__init__.py
jpholiday/exception.py
jpholiday/functions.py
jpholiday/jpholiday.py
jpholiday/cache/__init__.py
jpholiday/cache/in_memory.py
jpholiday/cache/interface.py
jpholiday/checker/__init__.py
jpholiday/checker/checker.py
jpholiday/checker/interface.py
jpholiday/checker/utils.py
jpholiday/model/__init__.py
jpholiday/model/holiday.py
jpholiday/registy/__init__.py
jpholiday/registy/interface.py
jpholiday/registy/registry.py
jpholiday-1.0.1.data/data/README.md
jpholiday-1.0.1.dist-info/licenses/LICENSE
jpholiday-1.0.1.dist-info/METADATA
jpholiday-1.0.1.dist-info/WHEEL
jpholiday-1.0.1.dist-info/top_level.txt
jpholiday-1.0.1.dist-info/RECORD
