Metadata-Version: 2.4
Name: jpholiday
Version: 1.0.1
Summary: Pure-Python Japan Public Holiday Generate
Home-page: https://github.com/Lalcs/jpholiday
Author: Vatis
Author-email: vatis@lalcs.com
License: MIT License
Keywords: Japan,Holiday
Platform: POSIX
Platform: Windows
Platform: Unix
Platform: MacOS
Classifier: Intended Audience :: Developers
Classifier: License :: OSI Approved :: MIT License
Classifier: Natural Language :: Japanese
Classifier: Operating System :: MacOS
Classifier: Operating System :: Microsoft
Classifier: Operating System :: POSIX
Classifier: Programming Language :: Python :: 3 :: Only
Classifier: Programming Language :: Python :: 3.9
Classifier: Programming Language :: Python :: 3.10
Classifier: Programming Language :: Python :: 3.11
Classifier: Programming Language :: Python :: 3.12
Classifier: Programming Language :: Python :: 3.13
License-File: LICENSE
Dynamic: author
Dynamic: author-email
Dynamic: classifier
Dynamic: description
Dynamic: description-content-type
Dynamic: home-page
Dynamic: keywords
Dynamic: license
Dynamic: license-file
Dynamic: platform
Dynamic: summary
